{
  "Mech Building" :
  {
  "Planning": "/rules/build-planning",
  "Selecting Components": "/rules/selecting-components",
  "Validating": "/rules/build-validating"
  },
  "Turn Based Play" :
  {
    "Combat": "/rules/combat",
    "Turn Structure": "/rules/turn-structure",
    "Weapons Specials": "/rules/weapon-specials"
  },
  "Maintenance" :
  {
    "Making Repairs": "/rules/making-repairs",
    "Maintenance Costs": "/rules/maintenance-costs",
    "Component States": "/rules/component-states",
    "Placing Components": "/rules/placing-components"
  },
  "Appendix" : {
    "Glossary": "/rules/glossary"
  }
}